todder/__init__.py
todder/_version.py
todder/signal.py
todder/tod.py
todder/coords/__init__.py
todder/coords/transforms.py
todder/instruments/__init__.py
todder/instruments/act/__init__.py
todder/instruments/act/della.py
todder/instruments/atlast/__init__.py
todder/instruments/mustang2/__init__.py
todder/sim/__init__.py
todder/sim/noise.py
todder/tests/__init__.py
todder/tests/conftest.py
todder/tests/test_tod.py
todder-0.0.4.dist-info/METADATA
todder-0.0.4.dist-info/WHEEL
todder-0.0.4.dist-info/licenses/LICENSE
todder-0.0.4.dist-info/RECORD
